CHANGES
MANIFEST.in
README
setup.py
try_imports.py
PySLIC.egg-info/PKG-INFO
PySLIC.egg-info/SOURCES.txt
PySLIC.egg-info/dependency_links.txt
PySLIC.egg-info/requires.txt
PySLIC.egg-info/top_level.txt
docs/Makefile
docs/conf.py
docs/index.rst
docs/tutorial.rst
pyslic/__init__.py
pyslic/pyslic_version.py
pyslic/utils.py
pyslic/features/__init__.py
pyslic/features/computefeatures.py
pyslic/features/edgefeatures.py
pyslic/features/featinfo.py
pyslic/features/hullfeatures.py
pyslic/features/imgfeatures.py
pyslic/features/imgmoments.py
pyslic/features/imgskelfeats.py
pyslic/features/noffeatures.py
pyslic/features/objectfeatures.py
pyslic/features/overlap.py
pyslic/features/pslidbinformat.py
pyslic/features/tas.py
pyslic/features/texture.py
pyslic/features/zernike.py
pyslic/image/__init__.py
pyslic/image/image.py
pyslic/image/io/__init__.py
pyslic/image/io/autoload.py
pyslic/image/io/dirtransversal.py
pyslic/image/io/ic100.py
pyslic/image/io/ksr.py
pyslic/image/io/read_cellomics_dib.py
pyslic/image/io/readimg.py
pyslic/image/io/readtjz.py
pyslic/image/io/tiff_pairs.py
pyslic/imageprocessing/__init__.py
pyslic/imageprocessing/objectdetection.py
pyslic/imageprocessing/thresholding.py
pyslic/preprocess/__init__.py
pyslic/preprocess/preprocess.py
pyslic/preprocess/preprocesscollection.py
pyslic/segmentation/__init__.py
pyslic/segmentation/active_masks.py
pyslic/segmentation/filters.py
pyslic/segmentation/nucleidetection.py
pyslic/segmentation/roysam.py
pyslic/segmentation/thresholding.py
pyslic/segmentation/voronoi.py
pyslic/segmentation/watershed.py