Metadata-Version: 1.0
Name: PySLIC
Version: 0.6.3
Summary: Subcellular Location Image Classifier
Home-page: http://murphylab.cbi.cmu.edu/
Author: Murphy Lab
Author-email: murphy@cmu.edu
License: UNKNOWN
Platform: UNKNOWN
